granite_common/.gitignore
granite_common/__init__.py
granite_common/_version.py
granite_common/optional.py
granite_common/util.py
granite_common/base/__init__.py
granite_common/base/io.py
granite_common/base/types.py
granite_common/granite3/__init__.py
granite_common/granite3/constants.py
granite_common/granite3/input.py
granite_common/granite3/output.py
granite_common/granite3/types.py
granite_common/granite3/granite32/__init__.py
granite_common/granite3/granite32/constants.py
granite_common/granite3/granite32/input.py
granite_common/granite3/granite32/output.py
granite_common/granite3/granite32/types.py
granite_common/granite3/granite33/__init__.py
granite_common/granite3/granite33/constants.py
granite_common/granite3/granite33/input.py
granite_common/granite3/granite33/output.py
granite_common/granite3/granite33/types.py
granite_common/intrinsics/__init__.py
granite_common/intrinsics/constants.py
granite_common/intrinsics/input.py
granite_common/intrinsics/json_util.py
granite_common/intrinsics/output.py
granite_common/intrinsics/types.py
granite_common/intrinsics/util.py
granite_common/retrievers/__init__.py
granite_common/retrievers/elasticsearch.py
granite_common/retrievers/embeddings.py
granite_common/retrievers/util.py
granite_common-0.3.6.dist-info/licenses/LICENSE
granite_common-0.3.6.dist-info/METADATA
granite_common-0.3.6.dist-info/WHEEL
granite_common-0.3.6.dist-info/top_level.txt
granite_common-0.3.6.dist-info/RECORD
